fe_polars/__init__.py
fe_polars/encoding/__init__.py
fe_polars/encoding/one_hot_encoding.py
fe_polars/encoding/target_encoding.py
fe_polars/imputing/__init__.py
fe_polars/imputing/base_imputing.py
feature_engineering_polars-0.5.0.dist-info/LICENSE
feature_engineering_polars-0.5.0.dist-info/METADATA
feature_engineering_polars-0.5.0.dist-info/WHEEL
feature_engineering_polars-0.5.0.dist-info/RECORD
