Metadata-Version: 2.1
Name: feature-engineering-polars
Version: 0.5.0
Summary: Feature engineering done with Polars
License: MIT
Author: Jordan Delbar
Author-email: jordandelbar@gmail.com
Requires-Python: >=3.9,<4.0
Classifier: License :: OSI Approved :: MIT License
Classifier: Programming Language :: Python :: 3
Classifier: Programming Language :: Python :: 3.9
Classifier: Programming Language :: Python :: 3.10
Classifier: Programming Language :: Python :: 3.11
Requires-Dist: polars (>=1.8.2,<2.0.0)
